bitcoinfees/__init__.py
bitcoinfees/client.py
tests/__init__.py
tests/test_bitcoinfees.py
bitcoinfees-0.0.3.dist-info/METADATA
bitcoinfees-0.0.3.dist-info/WHEEL
bitcoinfees-0.0.3.dist-info/top_level.txt
bitcoinfees-0.0.3.dist-info/RECORD
