Metadata-Version: 2.1
Name: bitcoinfees
Version: 0.0.3
Summary: UNKNOWN
Home-page: UNKNOWN
Author: daveusa31
License: UNKNOWN
Project-URL: Source, https://github.com/daveusa31/bitcoinfees
Platform: UNKNOWN
Classifier: Development Status :: 5 - Production/Stable
Classifier: Intended Audience :: Developers
Classifier: Natural Language :: Russian
Classifier: Programming Language :: Python
Classifier: Programming Language :: Python :: 3.5
Classifier: Programming Language :: Python :: 3.6
Classifier: Programming Language :: Python :: 3.7
Classifier: Programming Language :: Python :: 3.8
Requires-Python: >=3.5
Requires-Dist: requests (>=2.25.0)
